{"duration": 8.302885055541992, "input_args": {"imgs": "<nibabel.nifti1.Nifti1Image object at 0x7f81798e7190>", "extraction_function": "<nilearn.maskers.nifti_labels_masker._ExtractionFunctor object at 0x7f884a438340>", "parameters": "{'background_label': 0, 'detrend': True, 'dtype': None, 'high_pass': 0.009, 'high_variance_confounds': False, 'labels': None, 'labels_img': <nibabel.nifti1.Nifti1Image object at 0x7f884a438a60>, 'low_pass': 0.08, 'mask_img': None, 'reports': True, 'smoothing_fwhm': None, 'standardize': True, 'standardize_confounds': True, 'strategy': 'mean', 't_r': 2, 'target_shape': None, 'target_affine': None}", "confounds": "[array([[-5.98300000e-02,  1.52040000e-02,  3.15122000e-02, ...,\n        -1.80194166e+00,  1.19507568e+01, -1.75988561e+00],\n       [-8.20852000e-02,  4.15611000e-02, -1.66579000e-02, ...,\n        -9.02348389e-01, -8.42624957e+00,  2.54169902e+00],\n       [-1.87097000e-02, -3.62906000e-02, -1.26608000e-01, ...,\n        -4.00436194e+00, -7.72521210e+00, -7.89944357e+00],\n       ...,\n       [ 5.41967000e-03,  7.08336000e-02,  9.38234000e-02, ...,\n        -2.83785298e+00, -1.04818901e+01, -3.03000567e+00],\n       [-2.86107000e-03,  1.12611000e-01,  9.13441000e-02, ...,\n         2.44347531e+00,  7.01313467e+00,  1.55717118e+00],\n       [-1.69404000e-03,  8.38134000e-02,  7.69918000e-02, ...,\n        -2.39183362e+00, -3.88496197e+00, -2.02761844e+00]])]", "sample_mask": "None", "copy": "True", "dtype": "None"}}